LICENSE
MANIFEST.in
README.rst
setup.py
vdt/__init__.py
vdt.versionplugin.gitchain.egg-info/PKG-INFO
vdt.versionplugin.gitchain.egg-info/SOURCES.txt
vdt.versionplugin.gitchain.egg-info/dependency_links.txt
vdt.versionplugin.gitchain.egg-info/namespace_packages.txt
vdt.versionplugin.gitchain.egg-info/requires.txt
vdt.versionplugin.gitchain.egg-info/top_level.txt
vdt.versionplugin.gitchain.egg-info/zip-safe
vdt/versionplugin/__init__.py
vdt/versionplugin/gitchain/__init__.py
vdt/versionplugin/gitchain/freeze.py
vdt/versionplugin/gitchain/shared.py