Metadata-Version: 1.0
Name: vdt.versionplugin.gitchain
Version: 0.0.4
Summary: Instead of building packages as a freezed state, propagate tags between git repositories.
Home-page: UNKNOWN
Author: Lars van de Kerkhof
Author-email: lars@permanentmarkers.nl
License: UNKNOWN
Platform: UNKNOWN
